{
  "common": {
    "loading": "불러오는 중...",
    "loadingDots": "...",
    "loadingShort": "로딩 중…",
    "notOpen": "아직 오픈되지 않음",
    "connectWallet": "먼저 지갑을 연결하세요",
    "copyFailed": "복사 실패, 다시 시도해 주세요",
    "confirm": "확인",
    "cancel": "취소",
    "close": "닫기",
    "back": "뒤로",
    "available": "사용 가능",
    "unavailable": "사용 불가",
    "peopleUnit": "명",
    "balancePrefix": "잔액: ",
    "operationFailed": "작업 실패",
    "connectWalletBtn": "지갑 연결",
    "connectFirstBtn": "지갑 연결"
  },
  "nav": {
    "entrust": "보관",
    "earnings": "수익",
    "mine": "내 정보",
    "team": "팀"
  },
  "header": {
    "switchLanguage": "언어 변경",
    "connectWallet": "지갑 연결",
    "languageTitle": "언어 선택",
    "inviteCodeTitle": "초대 코드 입력",
    "inviteCodePlaceholder": "초대 코드를 입력하세요",
    "inviteCodeRequired": "초대 코드를 입력해 주세요",
    "registerSubmit": "제출",
    "walletManage": "지갑 관리",
    "selectWallet": "지갑 선택",
    "disconnect": "연결 해제",
    "bindInviteTitle": "초대 코드 연동",
    "bindInviteHint": "현재 계정에 초대 관계가 없습니다. 올바른 초대 코드를 입력한 후 계속하세요.",
    "inviteCodeEmpty": "초대 코드를 입력해 주세요",
    "connectWalletFirst": "먼저 지갑을 연결하세요",
    "loginProofExpired": "로그인 정보가 만료되었습니다. 지갑을 다시 연결하세요",
    "bindSuccess": "연동 완료",
    "bindPending": "연동 중...",
    "confirmBind": "연동 확인",
    "switchBscFailed": "BSC 네트워크 전환 실패",
    "registerFailed": "등록 실패",
    "connectWalletBtn": "지갑 연결",
    "confirmBindBtn": "확인",
    "bindPendingBtn": "연동 중",
    "disconnectBtn": "연결 해제",
    "walletManageBtn": "지갑",
    "selectWalletBtn": "지갑"
  },
  "wallet": {
    "noWallets": "사용 가능한 지갑이 감지되지 않았습니다",
    "connectFailed": "지갑 연결 또는 네트워크 전환 실패",
    "injectedDefault": "기본값(권장)",
    "loginFailed": "지갑 로그인 실패, 나중에 다시 시도해 주세요"
  },
  "entrust": {
    "buyTicket": "티켓 구매",
    "buyWhitelist": "화이트리스트 구매",
    "whitelistGateHint": "화이트리스트 구매 후 시스템을 이용할 수 있습니다. 결제 완료 후 자동으로 입장합니다.",
    "whitelistPaying": "결제 확인 중...",
    "ticketAirdropDesc": "{bnbAmount} BNB를 사용하여 {usdtAmount} USDT 에어드롭 받기",
    "projectPart1": "프로",
    "projectPart2": "정보",
    "worldCupPart1": "예측",
    "worldCupPart2": "WC",
    "announcementText": "생태계 진행 및 협력 최신 소식 AULONG 생태계 동향...",
    "announcementPanelTitle": "공지",
    "announcementNoRecords": "공지가 없습니다",
    "projectBannerDesc": "Aulong 프로젝트 비전, 경제 모델 및 AI 스마트 거래 메커니즘 알아보기",
    "startAiPart1": "시작",
    "startAiPart2": "AI",
    "startAiDesc": "스마트 위탁 전략 활성화",
    "strategyTrendTitle": "체험 전략",
    "strategyTrendDesc": "AI 기반 추세 포착, 추세에 순응하여 초과 수익 추구",
    "strategyArbitrageTitle": "심화 전략",
    "strategyArbitrageDesc": "다중 시장 차익거래 기회, 낮은 변동성의 안정적 수익",
    "strategyHedgeTitle": "안정형 전략",
    "strategyHedgeDesc": "시장 변동성 헤지, 안정적 낮은 낙폭 추구",
    "apr": "APR",
    "period": "기간",
    "periodUnit": "일",
    "start": "시작",
    "deployConnectWalletFirst": "먼저 지갑을 연결하세요",
    "deployAgentTitle": "Aulong 마이닝 풀",
    "deployAgentStrategySection": "Agent 전략",
    "deployAgentLabel": "Agent",
    "deployCyclePeriod": "순환 주기",
    "deployEstimatedApr": "예상 APR",
    "deployCustodyAsset": "스테이킹 자산",
    "deployCustodyAmount": "스테이킹 금액",
    "deployAmountPlaceholder": "수량 입력",
    "deployMax": "전액",
    "deployAvailableBalance": "가용 잔액: {balance} {asset}",
    "deploySuccess": "배포가 완료되었습니다",
    "deployTxConfirming": "온체인 확인 중...",
    "deployInvalidAmount": "유효한 수량을 입력하세요",
    "deployInsufficientBalance": "잔액이 부족합니다",
    "deployBelowMinAmount": "최소 예치 금액은 {min} USDT 입니다",
    "deployAboveMaxAmount": "최대 예치 금액은 {max} USDT 입니다",
    "deployDailyStakeLimitExceeded": "일일 배포 한도 {limit} USDT를 초과했습니다",
    "deployAccountMaxAmountExceeded": "계정 상한 {limit} USDT를 초과했습니다",
    "deployWhitelistRequired": "화이트리스트가 활성화되지 않아 작업할 수 없습니다",
    "aiStrategy": {
      "panelTitle": "AI 전략",
      "tabDeploying": "배포 중",
      "tabHistory": "운행 기록",
      "depositedAssets": "예치 자산",
      "cumulativeEarnings": "누적 수익",
      "runStatus": "운행 상태",
      "statusDeployed": "배포됨",
      "statusEnded": "종료",
      "statusRedeeming": "상환 중",
      "statusRedeemed": "상환 완료",
      "strategyName": "전략명",
      "startTime": "시작",
      "endTime": "종료",
      "runProgressPrefix": "운행 ",
      "runProgressMiddle": " 일/잔여 ",
      "runProgressSuffix": " 일",
      "redeemAfter": "{time} 후",
      "redeemable": "상환 가능",
      "redeemSuccess": "상환 신청이 완료되었습니다",
      "noRecords": "기록이 없습니다"
    },
    "aulPrice": "AUL 코인 가격",
    "holdAul": "해제 대기 AUL",
    "chartLoading": "로딩 중…",
    "chartLoadFailed": "데이터 로드 실패, 나중에 다시 시도해 주세요",
    "chartNoData": "{range} 데이터 없음",
    "range15m": "15분",
    "range1h": "1시간",
    "range1d": "1일",
    "rangeDescMinute": "분 단위 추세",
    "rangeDescHour": "시간 단위 추세",
    "rangeDescDay": "일 단위 추세",
    "buyWhitelistBtn": "화이트리스트",
    "projectBannerDescCard": "Aulong 비전·토크노믹스·AI 거래",
    "startAiDescCard": "스마트 위탁 전략 활성화",
    "projectsInfo": {
      "panelTitle": "프로젝트 자료",
      "heroBrand": "AULONG",
      "heroFinance": "금융",
      "heroSubtitle": "AI Agent 시스템",
      "heroDescPrefix": "더 낮은 진입장벽으로 전문 금융을 사용",
      "heroDescEmphasis": "AI Agent",
      "featureAgentContent": "금융 대모델, 시장 데이터, 온체인 정보, 전략 분석, 리스크 통제, 실행 능력을 통합해 복잡한 시스템 구축 없이도 전문 금융 AI Agent를 낮은 장벽으로 사용할 수 있습니다.",
      "roleUserTitle": "사용자",
      "roleUserBullet1": "목표 제시",
      "roleUserBullet2": "작업 설정",
      "roleUserBullet3": "결정 확인",
      "roleBrainTitle": "AULONG Brain",
      "roleBrainBullet1": "시장 이해",
      "roleBrainBullet2": "데이터 분석",
      "roleBrainBullet3": "전략 생성",
      "roleOsTitle": "AULONG OS",
      "roleOsBullet1": "Skill 스케줄",
      "roleOsBullet2": "리스크 제어",
      "roleOsBullet3": "기록/복기",
      "featureValueTitle": "AUL 생태 가치",
      "featureValueContent": "AUL은 생태 핵심 토큰으로서 에이전트 호출, 서비스 정산, 연산 자원, 생태 인센티브, 거버넌스 참여를 담당하며 사용자·에이전트·개발자·데이터 서비스·파트너를 하나의 가치 시스템으로 연결합니다.",
      "joinPrefix": "참여는",
      "joinEmphasis": "공동구축",
      "bottomPrefix": "금융 AI Agent의 미래를",
      "bottomSuffix": "에서 시작",
      "socialSectionTitle": "소셜 미디어",
      "aboutSectionTitle": "AuLong 소개",
      "socialYoutube": "YouTube",
      "socialX": "X",
      "socialTelegram": "Telegram",
      "socialParagraph": "Paragraph",
      "socialDapp": "Dapp",
      "socialLinktree": "Linktree",
      "aboutDriveZh": "중문 드라이브",
      "aboutDriveEn": "영문 드라이브",
      "aboutDriveKo": "한국어 드라이브",
      "aboutDriveVi": "베트남어 드라이브",
      "aboutNotionZh": "중문 자료库",
      "aboutNotionEn": "영문 자료库",
      "aboutNotionKo": "한국어 자료库",
      "aboutNotionVi": "베트남어 자료库"
    }
  },
  "team": {
    "currentLevel": "현재 등급",
    "smallAreaPerformance": "소구역 실적",
    "memberStats": "인원 통계",
    "directDetail": "직추천 상세",
    "teamPerformance": "팀 실적 데이터",
    "directPanelTitle": "직추천 상세",
    "noDirectRecords": "직추천 기록 없음",
    "loadFailed": "불러오기 실패, 나중에 다시 시도해 주세요",
    "registerTime": "가입 시간",
    "registerTimeValue": "가입 시간: {time}",
    "teamStakeTotal": "팀 위탁 총액",
    "teamStakeValue": "팀 위탁 총액: {amount}",
    "teamTotalRegisterCount": "팀 총 가입 인원: {count}",
    "teamWhiteListCount": "팀 화이트리스트 인원: {count}",
    "personalStake": "개인 위탁 금액",
    "directReferral": "직추천 위탁",
    "personalEntrustCount": "개인 위탁 수량",
    "peopleCount": "인원",
    "communityPerfYesterday": "소구역 실적(어제 변화)",
    "todayStakeTotal": "오늘 위탁 총액",
    "todayExperienceStrategy": "오늘 체험 전략(7일)",
    "totalExperienceStrategy": "체험 전략 누적(7일)",
    "todayAdvancedStrategy": "오늘 고급 전략(90일)",
    "totalAdvancedStrategy": "고급 전략 누적(90일)",
    "todayStableStrategy": "오늘 안정 전략(360일)",
    "totalStableStrategy": "안정 전략 누적(360일)",
    "teamTotalRegister": "팀 총 가입 인원",
    "teamTotalWhitelist": "팀 총 화이트리스트 수",
    "teamTotalStakers": "팀 총 위탁 인원",
    "todayNewWhitelist": "오늘 신규 화이트리스트 인원",
    "directPaginationAria": "직추천 상세 페이지네이션",
    "smallAreaPerformanceCard": "소구역 실적",
    "directReferralCard": "직추천",
    "personalEntrustCountCard": "개인 위탁",
    "teamIncome": "팀 보상",
    "referralIncome": "추천 보상"
  },
  "mine": {
    "totalAssets": "총 자산(USDT)",
    "totalEarnings": "출금 가능 잔액",
    "totalRelease": "출금 가능 잔액",
    "totalEntrustUsdt": "총 위탁",
    "totalUnreleasedAul": "해제 대기",
    "usdtWithdraw": "USDT 출금",
    "aulWithdraw": "AUL 출금",
    "xWithdraw": "X 출금",
    "goInvest": "투자하기",
    "swapTitle": "즉시 교환",
    "swapSubtitle": "AUL을 USDT로 빠르게 교환",
    "swapOpen": "즉시 교환 열기",
    "swapFromLabel": "From(소비)",
    "swapToLabel": "To(예상 수령)",
    "swapAvailableBalance": "사용 가능 잔액: {amount} {currency}",
    "swapInputPlaceholder": "입력하세요",
    "swapFillMaxAria": "전체 잔액 입력",
    "swapToggleAria": "스왑 방향 전환",
    "swapSuccess": "스왑이 완료되었습니다",
    "claim": "수령",
    "inviteFriends": "친구 초대",
    "inviteSubtitle": "전용 초대 보상, 링크 공유로 혜택 받기",
    "invitePart1": "친구",
    "invitePart2": "초대",
    "inviteOpen": "친구 초대 열기",
    "inviteCode": "초대 코드",
    "inviteLink": "초대 링크",
    "copyAllInvite": "초대 정보 전체 복사",
    "copyInviteCodeAria": "초대 코드 복사",
    "copyInviteLinkAria": "초대 링크 복사",
    "qrGenerating": "QR 코드 생성 중…",
    "inviteQrAlt": "초대 QR 코드",
    "fundDetails": "자금 내역",
    "filterBillType": "청구 유형",
    "filterCurrency": "통화",
    "filterTime": "시간",
    "fundFilter": {
      "billAll": "전체",
      "billStartAi": "AI 시작",
      "billUsdtYield": "USDT 수익",
      "billRedeem": "상환",
      "billRedeemFee": "상환 수수료 차감",
      "billXUnlock": "X 코인 잠금 해제",
      "billXWithdraw": "X 코인 출금",
      "billUsdtWithdraw": "USDT 출금",
      "billUsdtWithdrawFee": "USDT 출금 수수료 차감",
      "billShareholder": "주주 배당",
      "billTeamLevel": "팀 레벨 보상",
      "billTeamGen": "팀 세대 보상",
      "billTeamContrib": "팀 기여 보상",
      "currencyAll": "전체",
      "currencySearchPlaceholder": "통화명",
      "startDate": "시작일",
      "endDate": "종료일",
      "confirm": "확인"
    },
    "noFundRecords": "자금 내역 없음",
    "whitelist": "화이트리스트",
    "inactive": "ホワイトリストに登録されていません",
    "paginationAria": "자금 내역 페이지네이션",
    "prevPage": "이전 페이지",
    "nextPage": "다음 페이지",
    "morePagesAria": "더 많은 페이지",
    "usdtBtn": "USDT",
    "xBtn": "AUL",
    "claimBtn": "수령",
    "copyAllInviteBtn": "전체 복사",
    "withdrawPanelTitle": "출금",
    "withdrawRules": "출금 규칙",
    "withdrawCurrency": "통화",
    "withdrawAmount": "수량",
    "withdrawAmountPlaceholder": "최소 {min} USDT",
    "withdrawAulAmountPlaceholder": "최소 {min} AUL",
    "withdrawAll": "전체",
    "withdrawableUsdt": "출금 가능 잔액 USDT",
    "withdrawableAul": "출금 가능 잔액 AUL",
    "availableUsdt": "사용 가능 잔액 USDT",
    "availableAul": "사용 가능 잔액 AUL",
    "withdrawFee": "수수료",
    "withdrawExceedLimit": "출금 한도 초과",
    "withdrawAmountInvalid": "0보다 큰 출금 금액을 입력하세요",
    "withdrawInsufficientAulFee": "수수료를 지불할 AUL 잔액이 부족합니다",
    "withdrawClosed": "출금이 중단되었습니다",
    "withdrawUsdtClosed": "USDT 출금이 중단되었습니다",
    "withdrawUsdtBelowMin": "출금 금액은 {min} USDT 이상이어야 합니다",
    "withdrawUsdtAboveMax": "출금 금액은 {max} USDT 을 초과할 수 없습니다",
    "withdrawAulBelowMin": "출금 금액은 {min} AUL 이상이어야 합니다",
    "withdrawAulAboveMax": "출금 금액은 {max} AUL 을 초과할 수 없습니다",
    "withdrawSubmit": "지금 출금",
    "withdrawSuccess": "출금 신청이 완료되었습니다",
    "withdrawRecordTitle": "출금 기록",
    "withdrawRecordBtn": "출금 기록",
    "withdrawRecordFilterTime": "시간",
    "withdrawRecordFilterClear": "지우기",
    "withdrawRecordFilterStatus": "상태",
    "withdrawRecordStatusAll": "전체",
    "withdrawRecordStatusPending": "심사 대기",
    "withdrawRecordStatusSuccess": "성공",
    "withdrawRecordStatusRejected": "반려됨",
    "withdrawRecordRejectReason": "반려 사유: {reason}",
    "withdrawRecordFee": "수수료",
    "withdrawRecordEmpty": "출금 기록이 없습니다",
    "withdrawRecordLoadFailed": "출금 기록을 불러오지 못했습니다"
  },
  "earnings": {
    "totalEarnings": "AI 에이전트 총 수익(USDT)",
    "earningsRecord": "수익 기록",
    "claim": "수령",
    "pendingEarnings": "출금 가능 수익",
    "lastPeriodEarnings": "이전 기간 수익",
    "transactionRecord": "AULONG 에이전트 운행 기록",
    "realtime": "실시간",
    "noTransactions": "거래 기록 없음",
    "tradeTime": "거래 시간",
    "waitingConfirm": "확인 대기 중",
    "investBtn": "채굴하기",
    "claimBtn": "수령",
    "totalEarningsCard": "총 수익(USDT)",
    "earningsRecordCard": "수익 기록",
    "pendingEarningsCard": "미지급",
    "lastPeriodEarningsCard": "전기 수익",
    "lastPeriodHelpAria": "전기 수익 상세"
  },
  "worldCup": {
    "pageTitle": "예측",
    "tabAll": "전체",
    "tabHolding": "보유",
    "tabHistory": "기록",
    "categoryLabel": "분류",
    "categoryWorldCup": "WC",
    "filterTitle": "분류",
    "openCategoryFilter": "분류 필터",
    "statusOngoing": "진행",
    "statusEnded": "종료",
    "participateNow": "바로 참여",
    "matchTime": "경기 시간: ",
    "statusUpcoming": "예정",
    "statusOrdering": "주문중",
    "outcomeDraw": "무승부",
    "outcomeHomeWin": "{team} 승",
    "matchVs": "{home} vs {away}",
    "stakeAmount": "투입: ",
    "estimatedProfit": "예상 수익",
    "profit": "수익: ",
    "betAul": "베팅 AUL: ",
    "betTime": "베팅 시간: ",
    "betSide": "방향",
    "winLoss": "승패: ",
    "settlementAul": "정산 AUL: ",
    "settlementAulPrice": "정산 AUL 가격: ",
    "settlementTime": "정산 시간: ",
    "orderResultWin": "승",
    "orderResultLose": "패",
    "orderResultCancelled": "취소됨",
    "orderResultPending": "미정산",
    "resultScore": "{home} {homeScore}:{awayScore} {away}",
    "participate": "예측",
    "selectOutcomeFirst": "옵션을 선택하세요",
    "outcomeGroupAria": "예측 옵션",
    "stanceGroupAria": "예측 입장",
    "outcomeYes": "YES",
    "outcomeNo": "NO",
    "inputAmountUsdt": "금액 입력 (USDT)",
    "enterAmountFirst": "금액을 입력하세요",
    "insufficientAul": "AUL 잔액이 부족합니다",
    "availableBalance": "사용 가능: {balance} AUL",
    "currentAulPrice": "현재 AUL 가격",
    "aulToDeduct": "차감 AUL",
    "expectedWinUsdt": "예상 수익 (USDT)",
    "feeAul": "수수료 (AUL)",
    "detailNotFound": "경기를 찾을 수 없습니다",
    "noBetMarkets": "베팅 가능한 플레이가 없습니다",
    "orderSuccessTitle": "주문 완료",
    "orderSuccessDesc": "{outcome} 매수에 성공했습니다.",
    "orderStakeAmount": "투입 금액",
    "orderDeductAmount": "차감 수량",
    "orderStatus": "상태",
    "orderStatusSuccess": "주문 완료",
    "submitFailed": "주문에 실패했습니다. 다시 시도하세요.",
    "betAmountRange": "베팅 범위: {min} - {max} USDT",
    "amountBelowMin": "최소 베팅 {min} USDT",
    "amountAboveMax": "최대 베팅 {max} USDT",
    "emptyTitle": "주문 없음",
    "emptyDesc": "관련 데이터가 없습니다.",
    "loadFailed": "로드 실패",
    "paginationAria": "페이지",
    "prevPage": "이전",
    "nextPage": "다음",
    "leagues": {
      "nationsLeague": "네이션스리그",
      "groupA": "A조",
      "groupB": "B조",
      "groupC": "C조",
      "groupD": "D조",
      "groupE": "E조",
      "groupF": "F조",
      "groupG": "G조",
      "groupH": "H조",
      "quarterFinal": "8강",
      "semiFinal": "4강"
    },
    "teams": {
      "france": "프랑스",
      "portugal": "포르투갈",
      "brazil": "브라질",
      "argentina": "아르헨",
      "germany": "독일",
      "spain": "스페인",
      "england": "잉글랜드",
      "italy": "이탈리아",
      "japan": "일본",
      "korea": "한국",
      "netherlands": "네덜란드",
      "belgium": "벨기에",
      "mexico": "멕시코",
      "usa": "미국",
      "croatia": "크로아티아",
      "morocco": "모로코",
      "uruguay": "우루과이",
      "colombia": "콜롬비아",
      "australia": "호주",
      "saudi": "사우디"
    }
  },
  "toast": {
    "copiedInviteCode": "초대 코드가 복사되었습니다",
    "copiedInviteLink": "초대 링크가 복사되었습니다",
    "copiedAllInvite": "초대 정보가 복사되었습니다",
    "teamOverviewFailed": "팀 데이터 불러오기 실패",
    "updateUserFailed": "사용자 정보 업데이트 실패"
  },
  "locale": {
    "zh_CN": "简体中文",
    "en_US": "English",
    "ko_KR": "한국어",
    "vi_VN": "Tiếng Việt",
    "ja_JP": "日本語",
    "ms_MY": "Bahasa Melayu"
  }
}
